fullpath83replace/README.MD
fullpath83replace/__init__.py
fullpath83replace/requirements.txt
fullpath83replace/thirdparty.json
fullpath83replace-0.12.dist-info/LICENSE.rst
fullpath83replace-0.12.dist-info/METADATA
fullpath83replace-0.12.dist-info/WHEEL
fullpath83replace-0.12.dist-info/top_level.txt
fullpath83replace-0.12.dist-info/RECORD
