Metadata-Version: 2.1
Name: fullpath83replace
Version: 0.12
Summary: Converts long Windows file paths to their short 8.3 format in a string where applicable
Home-page: https://github.com/hansalemaos/fullpath83replace
Author: Johannes Fischer
Author-email: aulasparticularesdealemaosp@gmail.com
License: MIT
Keywords: convert,path,windows,83
Classifier: Development Status :: 4 - Beta
Classifier: Programming Language :: Python :: 3 :: Only
Classifier: Programming Language :: Python :: 3.10
Classifier: Topic :: Software Development :: Libraries :: Python Modules
Classifier: Topic :: Utilities
License-File: LICENSE.rst
